stx/__init__.py
stx/climate_controller.py
stx/errors.py
stx/memory_map.py
stx/plate_handler.py
stx/serial_port.py
stx/shaker_controller.py
stx/stx.py
stx/utils.py
open_liconic_stx-0.1.0.dist-info/LICENSE
open_liconic_stx-0.1.0.dist-info/METADATA
open_liconic_stx-0.1.0.dist-info/WHEEL
open_liconic_stx-0.1.0.dist-info/top_level.txt
open_liconic_stx-0.1.0.dist-info/RECORD
